document_parse/__init__.py
document_parse/llamaparse.py
document_parse/main_file_s3_to_llamaparse.py
mcp_pms/__init__.py
mcp_pms/__main__.py
mcp_pms/constants.py
mcp_pms/databases.py
mcp_pms/generate_mail_html.py
mcp_pms/html_link_from_md.py
mcp_pms/prompts.py
mcp_pms/resources.py
mcp_pms/server.py
mcp_pms/tool_schema.py
mcp_pms/tools.py
mcp_pms/utils.py
mcp_pms/Agent/main.py
mcp_pms/Agent/markdown_logger.py
mcp_pms/Agent/setup.py
mcp_pms/Agent/app/__init__.py
mcp_pms/Agent/app/bedrock.py
mcp_pms/Agent/app/config.py
mcp_pms/Agent/app/exceptions.py
mcp_pms/Agent/app/llm.py
mcp_pms/Agent/app/logger.py
mcp_pms/Agent/app/schema.py
mcp_pms/Agent/app/toolHandler.py
mcp_pms/Agent/app/agent/__init__.py
mcp_pms/Agent/app/agent/base.py
mcp_pms/Agent/app/agent/casefileAgent.py
mcp_pms/Agent/app/agent/react.py
mcp_pms/Agent/app/agent/toolcall.py
mcp_pms/Agent/app/sandbox/__init__.py
mcp_pms/Agent/app/sandbox/client.py
mcp_pms/Agent/app/sandbox/core/exceptions.py
mcp_pms/Agent/app/sandbox/core/manager.py
mcp_pms/Agent/app/sandbox/core/sandbox.py
mcp_pms/Agent/app/sandbox/core/terminal.py
mcp_pms/Agent/app/tool/__init__.py
mcp_pms/Agent/app/tool/base.py
mcp_pms/Agent/app/tool/create_chat_completion.py
mcp_pms/Agent/app/tool/mcp_tool.py
mcp_pms/Agent/app/tool/terminate.py
mcp_pms/Agent/app/tool/tool_collection.py
mcp_pms/Agent/app/tool/search/__init__.py
mcp_pms/Agent/app/tool/search/baidu_search.py
mcp_pms/Agent/app/tool/search/base.py
mcp_pms/Agent/app/tool/search/bing_search.py
mcp_pms/Agent/app/tool/search/duckduckgo_search.py
mcp_pms/Agent/app/tool/search/google_search.py
mcp_pms/Agent/app/tool/search/vessel_database_search.py
mcp_pms/Agent/app/tool/search/vessel_search.py
mcp_pms/Agent/config/config.toml
mcp_pms/Agent/config/mcp_servers_config.json
mcp_pms/Agent/config/tools.json
mcp_pms/scheduler/executor.py
mcp_pms/scheduler/schedule.py
utils/__init__.py
utils/llm.py
syia_mcp_pms_2025_x7k9-0.1.20.dist-info/METADATA
syia_mcp_pms_2025_x7k9-0.1.20.dist-info/WHEEL
syia_mcp_pms_2025_x7k9-0.1.20.dist-info/top_level.txt
syia_mcp_pms_2025_x7k9-0.1.20.dist-info/RECORD
